layer_cake/__init__.py
layer_cake/cake.py
layer_cake/constants.py
layer_cake/disco.py
layer_cake/discovery.py
layer_cake/dockerfile.py
layer_cake/knowledge.py
layer_cake/reactive.py
layer_cake/utils.py
layer_cake-0.1.4.dist-info/DESCRIPTION.rst
layer_cake-0.1.4.dist-info/METADATA
layer_cake-0.1.4.dist-info/RECORD
layer_cake-0.1.4.dist-info/WHEEL
layer_cake-0.1.4.dist-info/dependency_links.txt
layer_cake-0.1.4.dist-info/entry_points.txt
layer_cake-0.1.4.dist-info/metadata.json
layer_cake-0.1.4.dist-info/top_level.txt
